purepyodbc/__init__.py
purepyodbc/_connection.py
purepyodbc/_constants.py
purepyodbc/_cursor.py
purepyodbc/_driver_manager.py
purepyodbc/_dto.py
purepyodbc/_enums.py
purepyodbc/_environment.py
purepyodbc/_errors.py
purepyodbc/_handler.py
purepyodbc/_row.py
purepyodbc/_typedef.py
purepyodbc/py.typed
purepyodbc-0.1.0.dist-info/LICENSE
purepyodbc-0.1.0.dist-info/METADATA
purepyodbc-0.1.0.dist-info/WHEEL
purepyodbc-0.1.0.dist-info/RECORD
