Metadata-Version: 2.1
Name: purepyodbc
Version: 0.1.0
Summary: A pure python ODBC package
License: MIT
Author: Christopher McEvoy
Author-email: chris@chrismcevoy.net
Requires-Python: >=3.9,<4.0
Classifier: License :: OSI Approved :: MIT License
Classifier: Programming Language :: Python :: 3
Classifier: Programming Language :: Python :: 3.9
Classifier: Programming Language :: Python :: 3.10
Classifier: Programming Language :: Python :: 3.11
Classifier: Programming Language :: Python :: 3.12
